{
  "schemaVersion": 1,
  "date": "2026-02-18",
  "generatedAt": "2026-02-17T20:51:28.452Z",
  "events": {
    "upcoming": [
      {
        "sport": "olympics",
        "tournament": "Winter Olympics 2026",
        "title": "Cross-Country Skiing — Team Sprint Free",
        "time": "2026-02-18T09:45:00+01:00",
        "endTime": "2026-02-18T13:00:00+01:00",
        "venue": "Tesero Cross-Country Skiing Stadium",
        "norwegian": true,
        "streaming": [
          {
            "platform": "NRK",
            "type": "tv"
          }
        ],
        "participants": [],
        "norwegianPlayers": [
          {
            "name": "Johannes Hoesflot Klaebo"
          }
        ],
        "totalPlayers": null,
        "link": null,
        "status": null,
        "featuredGroups": [],
        "homeTeam": null,
        "awayTeam": null,
        "isFavorite": false,
        "context": "olympics-2026",
        "importance": 5,
        "importanceReason": "Klaebo in Olympic team sprint, Norway gold favourite",
        "summary": "Johannes Høsflot Klæbo anchors Norway's team sprint bid — Norway is heavy favourite in this flagship cross-country event.",
        "tags": [
          "must-watch",
          "final",
          "norwegian-player"
        ],
        "norwegianRelevance": 5,
        "enrichedAt": "2026-02-17T20:51:11.093Z"
      },
      {
        "sport": "olympics",
        "tournament": "Winter Olympics 2026",
        "title": "Biathlon — Women's 4x6km Relay",
        "time": "2026-02-18T14:45:00+01:00",
        "endTime": "2026-02-18T16:15:00+01:00",
        "venue": "Anterselva Biathlon Arena",
        "norwegian": true,
        "streaming": [
          {
            "platform": "NRK",
            "type": "tv"
          }
        ],
        "participants": [],
        "norwegianPlayers": [
          {
            "name": "Maren Kirkeeide"
          },
          {
            "name": "Ingrid Landmark Tandrevold"
          }
        ],
        "totalPlayers": null,
        "link": null,
        "status": null,
        "featuredGroups": [],
        "homeTeam": null,
        "awayTeam": null,
        "isFavorite": false,
        "context": "olympics-2026",
        "importance": 4,
        "importanceReason": "Norwegian biathletes in Olympic relay final",
        "summary": "Kirkeeide and Tandrevold lead Norway's women's biathlon relay — strong medal contenders at the Milan-Cortina Olympics.",
        "tags": [
          "must-watch",
          "final",
          "norwegian-player"
        ],
        "norwegianRelevance": 5,
        "enrichedAt": "2026-02-17T20:51:11.093Z"
      },
      {
        "sport": "football",
        "tournament": "Champions League",
        "title": "Newcastle United at FK Qarabag",
        "time": "2026-02-18T17:45:00.000Z",
        "endTime": null,
        "venue": "Tofiq Bahramov Republican Stadium",
        "meta": "Champions League • 1st Leg",
        "norwegian": false,
        "streaming": [
          {
            "platform": "TV 2 Play",
            "url": "https://play.tv2.no/sport/fotball/",
            "type": "streaming",
            "source": "tvkampen"
          },
          {
            "platform": "TV 2 Sport 1",
            "url": "https://play.tv2.no/sport/fotball/",
            "type": "tv",
            "source": "tvkampen"
          },
          {
            "platform": "Viaplay",
            "url": "https://viaplay.no/sport/fotball/",
            "type": "streaming",
            "source": "tvkampen"
          },
          {
            "platform": "Eurosport Norge",
            "url": "https://www.discoveryplus.no/sport",
            "type": "tv",
            "source": "tvkampen"
          },
          {
            "platform": "MAX",
            "url": "https://play.max.com/",
            "type": "streaming",
            "source": "tvkampen"
          }
        ],
        "participants": [],
        "norwegianPlayers": [],
        "totalPlayers": null,
        "link": null,
        "status": null,
        "featuredGroups": [],
        "homeTeam": "FK Qarabag",
        "awayTeam": "Newcastle United",
        "isFavorite": false,
        "streamingSource": "tvkampen",
        "streamingConfidence": 1,
        "importance": 3,
        "importanceReason": "Champions League knockout stage first leg",
        "summary": "Newcastle travel to Baku for a winnable Champions League first leg — English side favoured against Azerbaijani champions.",
        "tags": [
          "must-watch"
        ],
        "norwegianRelevance": 2,
        "enrichedAt": "2026-02-17T20:51:11.093Z"
      },
      {
        "sport": "football",
        "tournament": "La Liga",
        "title": "Villarreal at Levante",
        "time": "2026-02-18T19:00:00.000Z",
        "endTime": null,
        "venue": "Estadi Ciutat de València",
        "meta": "La Liga",
        "norwegian": false,
        "streaming": [
          {
            "platform": "Viaplay",
            "url": "https://viaplay.no/sport/fotball/",
            "type": "streaming",
            "source": "tvkampen"
          }
        ],
        "participants": [],
        "norwegianPlayers": [],
        "totalPlayers": null,
        "link": null,
        "status": null,
        "featuredGroups": [],
        "homeTeam": "Levante",
        "awayTeam": "Villarreal",
        "isFavorite": false,
        "streamingSource": "tvkampen",
        "streamingConfidence": 1,
        "importance": 2,
        "importanceReason": "Mid-table La Liga fixture, limited stakes",
        "summary": "Villarreal visit Levante in a routine La Liga match with limited title or relegation implications.",
        "tags": [
          "watchlist"
        ],
        "norwegianRelevance": 1,
        "enrichedAt": "2026-02-17T20:51:11.094Z"
      },
      {
        "sport": "football",
        "tournament": "Premier League",
        "title": "Arsenal at Wolverhampton Wanderers",
        "time": "2026-02-18T20:00:00.000Z",
        "endTime": null,
        "venue": "Molineux Stadium",
        "meta": "Premier League",
        "norwegian": false,
        "streaming": [
          {
            "platform": "Viaplay",
            "url": "https://viaplay.no/sport/fotball/",
            "type": "streaming",
            "source": "tvkampen"
          },
          {
            "platform": "Vsport",
            "url": "",
            "type": "unknown",
            "source": "tvkampen"
          }
        ],
        "participants": [],
        "norwegianPlayers": [],
        "totalPlayers": null,
        "link": null,
        "status": null,
        "featuredGroups": [],
        "homeTeam": "Wolverhampton Wanderers",
        "awayTeam": "Arsenal",
        "isFavorite": false,
        "streamingSource": "tvkampen",
        "streamingConfidence": 1,
        "importance": 4,
        "importanceReason": "Arsenal title challenge — must-win Premier League away fixture",
        "summary": "Arsenal visit Wolves in a crucial Premier League fixture as the Gunners chase the title — three points vital.",
        "tags": [
          "must-watch",
          "title-race"
        ],
        "norwegianRelevance": 2,
        "enrichedAt": "2026-02-17T20:51:11.094Z"
      },
      {
        "sport": "football",
        "tournament": "Champions League",
        "title": "Internazionale at Bodo/Glimt",
        "time": "2026-02-18T20:00:00.000Z",
        "endTime": null,
        "venue": "Aspmyra Stadion",
        "meta": "Champions League • 1st Leg",
        "norwegian": false,
        "streaming": [
          {
            "platform": "Check local listings",
            "url": "",
            "type": "info"
          }
        ],
        "participants": [],
        "norwegianPlayers": [],
        "totalPlayers": null,
        "link": null,
        "status": null,
        "featuredGroups": [],
        "homeTeam": "Bodo/Glimt",
        "awayTeam": "Internazionale",
        "isFavorite": false,
        "importance": 5,
        "importanceReason": "Norwegian club Bodø/Glimt host Inter Milan in Champions League",
        "summary": "Bodø/Glimt host Internazionale in a historic Champions League knockout tie — Norway's biggest club match in years.",
        "tags": [
          "must-watch",
          "final",
          "norwegian-team",
          "upset-potential"
        ],
        "norwegianRelevance": 5,
        "enrichedAt": "2026-02-17T20:51:11.094Z"
      },
      {
        "sport": "football",
        "tournament": "Champions League",
        "title": "Atlético Madrid at Club Brugge",
        "time": "2026-02-18T20:00:00.000Z",
        "endTime": null,
        "venue": "Jan Breydel Stadium",
        "meta": "Champions League • 1st Leg",
        "norwegian": false,
        "streaming": [
          {
            "platform": "TV 2 Play",
            "url": "https://play.tv2.no/sport/fotball/",
            "type": "streaming",
            "source": "tvkampen"
          },
          {
            "platform": "Viaplay",
            "url": "https://viaplay.no/sport/fotball/",
            "type": "streaming",
            "source": "tvkampen"
          },
          {
            "platform": "Eurosport Norge",
            "url": "https://www.discoveryplus.no/sport",
            "type": "tv",
            "source": "tvkampen"
          },
          {
            "platform": "MAX",
            "url": "https://play.max.com/",
            "type": "streaming",
            "source": "tvkampen"
          }
        ],
        "participants": [],
        "norwegianPlayers": [],
        "totalPlayers": null,
        "link": null,
        "status": null,
        "featuredGroups": [],
        "homeTeam": "Club Brugge",
        "awayTeam": "Atlético Madrid",
        "isFavorite": false,
        "streamingSource": "tvkampen",
        "streamingConfidence": 1,
        "importance": 4,
        "importanceReason": "Atlético Madrid in Champions League knockout stage",
        "summary": "Atlético Madrid face Club Brugge in a tightly contested Champions League first leg — Simeone's side slight favourites.",
        "tags": [
          "must-watch"
        ],
        "norwegianRelevance": 2,
        "enrichedAt": "2026-02-17T20:51:11.094Z"
      },
      {
        "sport": "football",
        "tournament": "Champions League",
        "title": "Bayer Leverkusen at Olympiacos",
        "time": "2026-02-18T20:00:00.000Z",
        "endTime": null,
        "venue": "Georgios Karaiskakis Stadium",
        "meta": "Champions League • 1st Leg",
        "norwegian": false,
        "streaming": [
          {
            "platform": "TV 2 Play",
            "url": "https://play.tv2.no/sport/fotball/",
            "type": "streaming",
            "source": "tvkampen"
          },
          {
            "platform": "Viaplay",
            "url": "https://viaplay.no/sport/fotball/",
            "type": "streaming",
            "source": "tvkampen"
          },
          {
            "platform": "Eurosport Norge",
            "url": "https://www.discoveryplus.no/sport",
            "type": "tv",
            "source": "tvkampen"
          },
          {
            "platform": "MAX",
            "url": "https://play.max.com/",
            "type": "streaming",
            "source": "tvkampen"
          }
        ],
        "participants": [],
        "norwegianPlayers": [],
        "totalPlayers": null,
        "link": null,
        "status": null,
        "featuredGroups": [],
        "homeTeam": "Olympiacos",
        "awayTeam": "Bayer Leverkusen",
        "isFavorite": false,
        "streamingSource": "tvkampen",
        "streamingConfidence": 0.7,
        "importance": 3,
        "importanceReason": "Champions League knockout stage opener, Leverkusen are strong favorites",
        "summary": "Leverkusen travel to Greece for the first leg of this Champions League last-32 tie as heavy favorites.",
        "tags": [
          "must-watch"
        ],
        "norwegianRelevance": 2,
        "enrichedAt": "2026-02-17T20:51:11.094Z"
      }
    ],
    "results": []
  },
  "matchResults": [],
  "standings": null,
  "watchPlan": null,
  "rssHighlights": null,
  "meta": {
    "eventCount": 8,
    "sportsCovered": [
      "olympics",
      "football"
    ],
    "hasResults": false,
    "hasStandings": false
  }
}