{
  "blocks": [
    {
      "type": "headline",
      "text": "Norway's Olympic Gold Rush Continues Before Arsenal's Title Test"
    },
    {
      "type": "narrative",
      "text": "Wednesday marks a landmark day for Norwegian winter sport. Klaebo anchors the team sprint at 09:45, then the women's biathlon relay crew chase gold at 14:45—two events where Norway enters as heavy favorites."
    },
    {
      "type": "divider",
      "text": ""
    },
    {
      "type": "event-line",
      "text": "⚽ 21:00 | Arsenal at Wolves — Title race clash; Arsenal need three points to maintain pressure on City"
    }
  ],
  "_meta": {
    "date": "2026-02-18",
    "mode": "preview",
    "generatedAt": "2026-02-17T00:46:55.193Z",
    "eventFingerprint": "e7eb9ceb46a6"
  }
}