{
  "generatedAt": "2026-03-18T10:23:24.907Z",
  "provider": "rules-only",
  "snapshot": {
    "totalEvents": 48,
    "sports": [
      "f1",
      "football",
      "golf",
      "tennis",
      "chess",
      "esports",
      "cycling"
    ],
    "bands": {
      "live": [],
      "today": [
        "Newcastle United at Barcelona",
        "Atalanta at Bayern Munich",
        "Galatasaray at Liverpool",
        "Atlético Madrid at Tottenham Hotspur"
      ],
      "tomorrow": [
        "Valspar Championship",
        "Hainan Classic pres. by MAEXTRO"
      ],
      "thisWeek": [
        "Manchester United at AFC Bournemouth",
        "Real Sociedad at Villarreal",
        "Puerto Vallarta Open",
        "Liverpool at Brighton & Hove Albion",
        "Mallorca at Elche",
        "Burnley at Fulham",
        "Crystal Palace at Manchester City",
        "Getafe at Espanyol",
        "Chelsea at Everton",
        "Real Oviedo at Levante",
        "Girona at Osasuna",
        "Brentford at Leeds United",
        "Valencia at Sevilla",
        "Sunderland at Newcastle United",
        "Rayo Vallecano at Barcelona",
        "West Ham United at Aston Villa",
        "Nottingham Forest at Tottenham Hotspur",
        "Alavés at Celta Vigo",
        "Real Betis at Athletic Club",
        "Atlético Madrid at Real Madrid",
        "Dubrovnik Open"
      ],
      "later": [
        "Round 1 – FIDE Candidates Tournament 2026",
        "Round 1 – Grenke Chess Festival 2026 | Freestyle Open A",
        "PGL CS2 Major Bucharest 2026",
        "Giro d'Italia 2026",
        "Tour of Norway 2026",
        "FIFA World Cup 2026 — Group Stage (Week 1)",
        "FIFA World Cup 2026 — Opening Match",
        "FIFA World Cup 2026 — Group Stage (Week 2)",
        "Tour de France 2026",
        "FIFA World Cup 2026 — Group Stage (Final Matchday)",
        "FIFA World Cup 2026 — Round of 32",
        "FIFA World Cup 2026 — Round of 16",
        "FIFA World Cup 2026 — Quarterfinals",
        "FIFA World Cup 2026 — Semifinal 1",
        "FIFA World Cup 2026 — Semifinal 2",
        "FIFA World Cup 2026 — Third Place Match",
        "FIFA World Cup 2026 Final",
        "Arctic Race of Norway 2026",
        "Vuelta a España 2026",
        "UCI Road World Championships 2026"
      ],
      "ended": [
        "Heineken Chinese Grand Prix"
      ]
    },
    "featuredBlockCount": 7,
    "briefPresent": true,
    "pipelineStatus": "warning",
    "editorialScore": 100,
    "issueCount": 8
  },
  "findings": [
    {
      "severity": "warning",
      "check": "event_too_far",
      "message": "\"Round 1 – Grenke Chess Festival 2026 | Freestyle Open A\" is 15 days away — may clutter the dashboard"
    },
    {
      "severity": "warning",
      "check": "event_too_far",
      "message": "\"PGL CS2 Major Bucharest 2026\" is 19 days away — may clutter the dashboard"
    },
    {
      "severity": "warning",
      "check": "event_too_far",
      "message": "\"Giro d'Italia 2026\" is 45 days away — may clutter the dashboard"
    },
    {
      "severity": "warning",
      "check": "event_too_far",
      "message": "\"Tour of Norway 2026\" is 55 days away — may clutter the dashboard"
    },
    {
      "severity": "warning",
      "check": "event_too_far",
      "message": "\"FIFA World Cup 2026 — Group Stage (Week 1)\" is 86 days away — may clutter the dashboard"
    },
    {
      "severity": "warning",
      "check": "event_too_far",
      "message": "\"FIFA World Cup 2026 — Opening Match\" is 86 days away — may clutter the dashboard"
    },
    {
      "severity": "warning",
      "check": "event_too_far",
      "message": "\"FIFA World Cup 2026 — Group Stage (Week 2)\" is 96 days away — may clutter the dashboard"
    },
    {
      "severity": "warning",
      "check": "event_too_far",
      "message": "\"Tour de France 2026\" is 101 days away — may clutter the dashboard"
    },
    {
      "severity": "warning",
      "check": "event_too_far",
      "message": "\"FIFA World Cup 2026 — Group Stage (Final Matchday)\" is 103 days away — may clutter the dashboard"
    },
    {
      "severity": "warning",
      "check": "event_too_far",
      "message": "\"FIFA World Cup 2026 — Round of 32\" is 108 days away — may clutter the dashboard"
    },
    {
      "severity": "warning",
      "check": "event_too_far",
      "message": "\"FIFA World Cup 2026 — Round of 16\" is 112 days away — may clutter the dashboard"
    },
    {
      "severity": "warning",
      "check": "event_too_far",
      "message": "\"FIFA World Cup 2026 — Quarterfinals\" is 116 days away — may clutter the dashboard"
    },
    {
      "severity": "warning",
      "check": "event_too_far",
      "message": "\"FIFA World Cup 2026 — Semifinal 1\" is 119 days away — may clutter the dashboard"
    },
    {
      "severity": "warning",
      "check": "event_too_far",
      "message": "\"FIFA World Cup 2026 — Semifinal 2\" is 120 days away — may clutter the dashboard"
    },
    {
      "severity": "warning",
      "check": "event_too_far",
      "message": "\"FIFA World Cup 2026 — Third Place Match\" is 123 days away — may clutter the dashboard"
    },
    {
      "severity": "warning",
      "check": "event_too_far",
      "message": "\"FIFA World Cup 2026 Final\" is 123 days away — may clutter the dashboard"
    },
    {
      "severity": "warning",
      "check": "event_too_far",
      "message": "\"Arctic Race of Norway 2026\" is 147 days away — may clutter the dashboard"
    },
    {
      "severity": "warning",
      "check": "event_too_far",
      "message": "\"Vuelta a España 2026\" is 157 days away — may clutter the dashboard"
    },
    {
      "severity": "warning",
      "check": "event_too_far",
      "message": "\"UCI Road World Championships 2026\" is 186 days away — may clutter the dashboard"
    },
    {
      "severity": "warning",
      "check": "featured_unknown_athlete",
      "message": "Featured mentions \"Now Newcastle\" but no matching athlete found in events data"
    },
    {
      "severity": "warning",
      "check": "featured_unknown_athlete",
      "message": "Featured mentions \"English\" but no matching athlete found in events data"
    },
    {
      "severity": "warning",
      "check": "featured_unknown_athlete",
      "message": "Featured mentions \"Both\" but no matching athlete found in events data"
    },
    {
      "severity": "warning",
      "check": "featured_unknown_athlete",
      "message": "Featured mentions \"Tyne\" but no matching athlete found in events data"
    },
    {
      "severity": "warning",
      "check": "featured_unknown_athlete",
      "message": "Featured mentions \"Wear\" but no matching athlete found in events data"
    },
    {
      "severity": "info",
      "check": "norwegian_flag_no_players",
      "message": "\"Round 1 – FIDE Candidates Tournament 2026\" marked norwegian=true but has no norwegianPlayers"
    },
    {
      "severity": "info",
      "check": "norwegian_flag_no_players",
      "message": "\"Round 1 – Grenke Chess Festival 2026 | Freestyle Open A\" marked norwegian=true but has no norwegianPlayers"
    },
    {
      "severity": "warning",
      "check": "result_all_recaps_null",
      "message": "All 36 football results have null recapHeadline — RSS matching may be broken"
    }
  ],
  "summary": {
    "total": 27,
    "critical": 0,
    "warning": 25,
    "info": 2
  },
  "pass": true,
  "tokenUsage": null
}