{
  "generatedAt": "2026-07-18T22:10:00.754Z",
  "latest": {
    "checkedAt": "2026-07-18T22:10:00.753Z",
    "sessionPct": 51,
    "weekPct": 77,
    "status": "amber"
  },
  "weekTrend24hPct": 25,
  "last7d": {
    "samples": 68,
    "peakWeekPct": 100,
    "avgWeekPct": 48,
    "peakSessionPct": 100,
    "amberHours": 5,
    "redHours": 9
  },
  "last30d": {
    "samples": 119,
    "peakWeekPct": 100,
    "avgWeekPct": 46,
    "peakSessionPct": 100,
    "amberHours": 14,
    "redHours": 15
  }
}