{
  "generatedAt": "2026-07-21T18:43:13.921Z",
  "latest": {
    "checkedAt": "2026-07-21T18:43:13.920Z",
    "sessionPct": 0,
    "weekPct": 33,
    "status": "green"
  },
  "weekTrend24hPct": 23,
  "last7d": {
    "samples": 71,
    "peakWeekPct": 100,
    "avgWeekPct": 48,
    "peakSessionPct": 100,
    "amberHours": 6,
    "redHours": 16
  },
  "last30d": {
    "samples": 147,
    "peakWeekPct": 100,
    "avgWeekPct": 46,
    "peakSessionPct": 100,
    "amberHours": 18,
    "redHours": 22
  }
}