{
  "generatedAt": "2026-07-17T14:06:39.257Z",
  "latest": {
    "checkedAt": "2026-07-17T14:06:39.256Z",
    "sessionPct": 6,
    "weekPct": 40,
    "status": "green"
  },
  "weekTrend24hPct": 24,
  "last7d": {
    "samples": 64,
    "peakWeekPct": 100,
    "avgWeekPct": 38,
    "peakSessionPct": 100,
    "amberHours": 3,
    "redHours": 9
  },
  "last30d": {
    "samples": 101,
    "peakWeekPct": 100,
    "avgWeekPct": 44,
    "peakSessionPct": 100,
    "amberHours": 12,
    "redHours": 15
  }
}